time_series_profiler-1.1.0.dist-info/licenses/LICENSE
tsp/__init__.py
tsp/config.py
tsp/types.py
tsp/adapters/__init__.py
tsp/adapters/pandas_adapter.py
tsp/profiling/__init__.py
tsp/profiling/registry.py
tsp/profiling/report.py
tsp/profiling/runner.py
tsp/profiling/metrics/__init__.py
tsp/profiling/metrics/basic_stats.py
tsp/profiling/metrics/categorical_profile.py
tsp/profiling/metrics/gaps_sampling.py
time_series_profiler-1.1.0.dist-info/METADATA
time_series_profiler-1.1.0.dist-info/WHEEL
time_series_profiler-1.1.0.dist-info/top_level.txt
time_series_profiler-1.1.0.dist-info/RECORD
