Metadata-Version: 2.4
Name: time-series-profiler
Version: 1.1.0
Summary: A clean adapter-pattern library for profiling time-series data
Author: Time Series Profiler Contributors
Maintainer: Time Series Profiler Contributors
License-Expression: Apache-2.0
Project-URL: Homepage, https://github.com/adilsaid/time-series-profiler
Project-URL: Documentation, https://github.com/adilsaid/time-series-profiler#readme
Project-URL: Repository, https://github.com/adilsaid/time-series-profiler.git
Project-URL: Issues, https://github.com/adilsaid/time-series-profiler/issues
Project-URL: Changelog, https://github.com/adilsaid/time-series-profiler/blob/main/CHANGELOG.md
Keywords: time-series,profiling,data-analysis,pandas,statistics
Classifier: Programming Language :: Python :: 3
Requires-Python: >=3.9
License-File: LICENSE
Requires-Dist: pandas>=2.0
Requires-Dist: numpy>=1.24
Requires-Dist: jinja2>=3.1
Provides-Extra: dev
Requires-Dist: pytest>=7.0; extra == "dev"
Requires-Dist: ruff>=0.1.6; extra == "dev"
Requires-Dist: mypy>=1.0; extra == "dev"
Requires-Dist: pre-commit>=3.0; extra == "dev"
Requires-Dist: python-semantic-release>=8.0; extra == "dev"
Dynamic: license-file
